{
  "project_info": {
    "project_number": "126749499148",
    "project_id": "chatapp-4a506",
    "storage_bucket": "chatapp-4a506.firebasestorage.app"
  },
  "client": [
    {
      "client_info": {
        "mobilesdk_app_id": "1:126749499148:android:176b86c3ea626bb924b329",
        "android_client_info": {
          "package_name": "com.machinetest"
        }
      },
      "oauth_client": [],
      "api_key": [
        {
          "current_key": "AIzaSyAyec_mt9id0TwTVvsbDT-uc3AHCb8STNE"
        }
      ],
      "services": {
        "appinvite_service": {
          "other_platform_oauth_client": []
        }
      }
    }
  ],
  "configuration_version": "1"
}